django_ca_cmc/__init__.py
django_ca_cmc/admin.py
django_ca_cmc/apps.py
django_ca_cmc/cmc.py
django_ca_cmc/conf.py
django_ca_cmc/constants.py
django_ca_cmc/hash.py
django_ca_cmc/models.py
django_ca_cmc/py.typed
django_ca_cmc/tests.py
django_ca_cmc/urls.py
django_ca_cmc/utils.py
django_ca_cmc/views.py
django_ca_cmc/management/__init__.py
django_ca_cmc/management/commands/__init__.py
django_ca_cmc/management/commands/cmc_add_client.py
django_ca_cmc/management/commands/cmc_list_clients.py
django_ca_cmc/migrations/0001_initial.py
django_ca_cmc/migrations/0002_alter_cmcclient_options_cmcclient_copy_extensions.py
django_ca_cmc/migrations/__init__.py
django_ca_cmc-0.0.1.dist-info/METADATA
django_ca_cmc-0.0.1.dist-info/WHEEL
django_ca_cmc-0.0.1.dist-info/top_level.txt
django_ca_cmc-0.0.1.dist-info/RECORD
