Metadata-Version: 2.2
Name: django-ca-cmc
Version: 0.0.1
Summary: django-ca plugin for Certificate Management over CMS (CMC)
Author-email: Mathias Ertl <mati@er.tl>
Project-URL: Homepage, https://github.com/mathiasertl/django-ca-cmc/
Project-URL: Source, https://github.com/mathiasertl/django-ca-cmc/
Project-URL: Issues, https://github.com/mathiasertl/django-ca-cmc/issues
Classifier: Development Status :: 5 - Production/Stable
Classifier: Framework :: Django :: 4.2
Classifier: Framework :: Django :: 5.1
Classifier: Framework :: Django
Classifier: Intended Audience :: Developers
Classifier: Intended Audience :: System Administrators
Classifier: License :: OSI Approved :: GNU General Public License v3 or later (GPLv3+)
Classifier: Programming Language :: Python :: 3
Classifier: Programming Language :: Python :: 3.11
Classifier: Programming Language :: Python :: 3.12
Classifier: Programming Language :: Python :: 3.13
Classifier: Programming Language :: Python :: 3 :: Only
Classifier: Topic :: Security :: Cryptography
Classifier: Topic :: Security
Classifier: Typing :: Typed
Requires-Python: >=3.11
Requires-Dist: django-ca>=2.1.1
Requires-Dist: python-cmc>=1.22
Requires-Dist: tabulate>=0.9.0
